example/__init__.py
example/main.py
example/utils.py
example/core/__init__.py
example/core/database.py
example/core/dependencies.py
relative2absolute/__init__.py
relative2absolute/cli.py
relative2absolute/core.py
relative2absolute-0.1.3.dist-info/METADATA
relative2absolute-0.1.3.dist-info/WHEEL
relative2absolute-0.1.3.dist-info/entry_points.txt
relative2absolute-0.1.3.dist-info/top_level.txt
relative2absolute-0.1.3.dist-info/RECORD
