Metadata-Version: 2.4
Name: relative2absolute
Version: 0.1.3
Summary: Convert relative imports in a Python package to absolute imports.
Author: Sami Jneidy
Author-email: samihanijneidy@gmail.com
Classifier: Programming Language :: Python :: 3
Classifier: License :: OSI Approved :: MIT License
Classifier: Operating System :: OS Independent
Requires-Python: >=3.7
Dynamic: author
Dynamic: author-email
Dynamic: classifier
Dynamic: description
Dynamic: description-content-type
Dynamic: requires-python
Dynamic: summary
